README.md
setup.py
waybackprov.py
waybackprov.egg-info/PKG-INFO
waybackprov.egg-info/SOURCES.txt
waybackprov.egg-info/dependency_links.txt
waybackprov.egg-info/entry_points.txt
waybackprov.egg-info/top_level.txt