Metadata-Version: 2.1
Name: waybackprov
Version: 0.0.1
Summary: Checks the provenance of a URL in the Wayback machine
Home-page: https://github.com/edsu/waybackprov
Author: Ed Summers
Author-email: ehs@pobox.com
License: UNKNOWN
Platform: UNKNOWN
Requires-Python: >=2.7
